bfs_scrape/__init__.py
bfs_scrape/bfs_web_scraper.py
bfs_scrape/cli.py
bfs_scrape/structured_outputs.py
bfs_scrape/system_prompt.py
bfscrape-0.1.0.dist-info/licenses/LICENSE
bfscrape-0.1.0.dist-info/METADATA
bfscrape-0.1.0.dist-info/WHEEL
bfscrape-0.1.0.dist-info/entry_points.txt
bfscrape-0.1.0.dist-info/top_level.txt
bfscrape-0.1.0.dist-info/RECORD
