Metadata-Version: 2.4
Name: bfscrape
Version: 0.1.0
Summary: A concurrent, AI-driven breadth-first web scraper
Author: BFScrape Developers
License-Expression: MIT
Project-URL: Homepage, https://github.com/yourusername/bfscrape
Project-URL: Bug Tracker, https://github.com/yourusername/bfscrape/issues
Keywords: web scraping,breadth-first search,ai,selenium,beautifulsoup
Classifier: Programming Language :: Python :: 3
Classifier: Operating System :: OS Independent
Requires-Python: >=3.8
License-File: LICENSE
Requires-Dist: selenium
Requires-Dist: beautifulsoup4
Requires-Dist: pydantic
Requires-Dist: openai>=1.0.0
Provides-Extra: dev
Requires-Dist: pytest; extra == "dev"
Requires-Dist: pytest-cov; extra == "dev"
Requires-Dist: black; extra == "dev"
Requires-Dist: isort; extra == "dev"
Requires-Dist: mypy; extra == "dev"
Requires-Dist: ruff; extra == "dev"
Dynamic: license-file
